interrofont/__init__.py
interrofont-0.1.2.dist-info/entry_points.txt
interrofont-0.1.2.dist-info/WHEEL
interrofont-0.1.2.dist-info/METADATA
interrofont-0.1.2.dist-info/RECORD
