Metadata-Version: 2.1
Name: interrofont
Version: 0.1.2
Summary: Interrogate a font file
License: MIT
Author: Simon Cozens
Author-email: simon@simon-cozens.org
Requires-Python: >=3,<4
Classifier: License :: OSI Approved :: MIT License
Classifier: Programming Language :: Python :: 3
Classifier: Programming Language :: Python :: 3.4
Classifier: Programming Language :: Python :: 3.5
Classifier: Programming Language :: Python :: 3.6
Classifier: Programming Language :: Python :: 3.7
Classifier: Programming Language :: Python :: 3.8
Requires-Dist: fonttools
